simple_dataclass_settings.py
simple_dataclass_settings-0.0.5.dist-info/LICENSE.md
simple_dataclass_settings-0.0.5.dist-info/METADATA
simple_dataclass_settings-0.0.5.dist-info/WHEEL
simple_dataclass_settings-0.0.5.dist-info/top_level.txt
simple_dataclass_settings-0.0.5.dist-info/RECORD
