Metadata-Version: 2.1
Name: simple_dataclass_settings
Version: 0.0.5
Summary: Simple library on top of dataclasses to create shiny-looking configs from environment variables.
Author-email: Egor Stakhovsky <y.stakhovsky@gmail.com>
Project-URL: Homepage, https://github.com/stakhovsky/simple-dataclass-settings
Project-URL: Bug Tracker, https://github.com/stakhovsky/simple-dataclass-settings/issues
Classifier: Programming Language :: Python :: 3
Classifier: License :: Other/Proprietary License
Classifier: Operating System :: OS Independent
Requires-Python: >=3.8
License-File: LICENSE.md
